databloom/__init__.py
databloom/api/__init__.py
databloom/api/credentials.py
databloom/api/nessie_metadata.py
databloom/connector/__init__.py
databloom/connector/base.py
databloom/connector/ggsheet.py
databloom/connector/mysql.py
databloom/connector/postgresql.py
databloom/datasets/__init__.py
databloom/datasets/dataset.py
databloom_connector-2.0.1.dist-info/METADATA
databloom_connector-2.0.1.dist-info/WHEEL
databloom_connector-2.0.1.dist-info/top_level.txt
databloom_connector-2.0.1.dist-info/RECORD
