Metadata-Version: 2.4
Name: databloom-connector
Version: 2.0.1
Summary: DataBloom Connector Package for Data Integration
Home-page: https://github.com/databloom-ai/databloom-connector
Author: DataBloom Team
Author-email: team@databloom.ai
Keywords: databloom,data integration,connector,database,warehouse
Classifier: Development Status :: 5 - Production/Stable
Classifier: Intended Audience :: Developers
Classifier: License :: OSI Approved :: MIT License
Classifier: Operating System :: OS Independent
Classifier: Programming Language :: Python :: 3
Classifier: Programming Language :: Python :: 3.9
Classifier: Programming Language :: Python :: 3.10
Classifier: Programming Language :: Python :: 3.11
Classifier: Topic :: Software Development :: Libraries :: Python Modules
Classifier: Topic :: Database
Requires-Python: >=3.9
Requires-Dist: pandas>=2.2.3
Requires-Dist: psycopg2-binary>=2.9.10
Requires-Dist: sqlalchemy>=2.0.38
Requires-Dist: trino>=0.333.0
Requires-Dist: pyspark>=3.5.1
Requires-Dist: requests>=2.31.0
Requires-Dist: duckdb>=0.10.0
Requires-Dist: mysql-connector-python>=8.0.0
Requires-Dist: gspread>=6.0.0
Requires-Dist: google-auth>=2.28.0
Requires-Dist: google-auth-oauthlib>=1.2.0
Requires-Dist: google-auth-httplib2>=0.2.0
Provides-Extra: dev
Requires-Dist: pytest>=8.0.0; extra == "dev"
Requires-Dist: pytest-cov>=4.1.0; extra == "dev"
Requires-Dist: black>=24.0.0; extra == "dev"
Requires-Dist: isort>=5.13.0; extra == "dev"
Requires-Dist: flake8>=7.0.0; extra == "dev"
Requires-Dist: twine>=4.0.0; extra == "dev"
Requires-Dist: build>=1.0.0; extra == "dev"
Dynamic: author
Dynamic: author-email
Dynamic: classifier
Dynamic: description
Dynamic: description-content-type
Dynamic: home-page
Dynamic: keywords
Dynamic: provides-extra
Dynamic: requires-dist
Dynamic: requires-python
Dynamic: summary
